MANIFEST.in
README.rst
setup.cfg
setup.py
tests/__init__.py
tests/basetest.py
tests/test_client.py
tests/test_keyword.py
tests/test_listing.py
venturocket/__init__.py
venturocket/abstractclient.py
venturocket/client.py
venturocket/keyword.py
venturocket/listing.py
venturocket.egg-info/PKG-INFO
venturocket.egg-info/SOURCES.txt
venturocket.egg-info/dependency_links.txt
venturocket.egg-info/requires.txt
venturocket.egg-info/top_level.txt