Metadata-Version: 1.1
Name: venturocket
Version: 1.0.0
Summary: The official python client library for Venturocket's API
Home-page: https://github.com/Venturocket/venturocket-api-python
Author: Joe Linn
Author-email: UNKNOWN
License: LICENSE
Platform: UNKNOWN
Classifier: Intended Audience :: Developers
Classifier: Development Status :: 5 - Production/Stable
Classifier: Operating System :: OS Independent
Classifier: Programming Language :: Python
Classifier: Topic :: Internet :: WWW/HTTP
